crunch_convert/__init__.py
crunch_convert/__main__.py
crunch_convert/__version__.py
crunch_convert/_model.py
crunch_convert/_utils.py
crunch_convert/cli.py
crunch_convert/notebook/__init__.py
crunch_convert/notebook/_model.py
crunch_convert/notebook/_notebook.py
crunch_convert/notebook/_r.py
crunch_convert/notebook/_utils.py
crunch_convert/requirements_txt/__init__.py
crunch_convert/requirements_txt/_formatter.py
crunch_convert/requirements_txt/_freeze.py
crunch_convert/requirements_txt/_model.py
crunch_convert/requirements_txt/_parse.py
crunch_convert/requirements_txt/_whitelist.py
crunch_convert-0.7.0.dist-info/METADATA
crunch_convert-0.7.0.dist-info/WHEEL
crunch_convert-0.7.0.dist-info/entry_points.txt
crunch_convert-0.7.0.dist-info/top_level.txt
crunch_convert-0.7.0.dist-info/RECORD
