Metadata-Version: 2.4
Name: crunch-convert
Version: 0.7.0
Summary: crunch-convert - Conversion module for the CrunchDAO Platform
Home-page: https://github.com/crunchdao/crunch-convert
Author: Enzo CACERES
Author-email: enzo.caceres@crunchdao.com
Keywords: package development template
Classifier: Intended Audience :: Developers
Classifier: Programming Language :: Python :: 3.7
Requires-Python: >=3
Requires-Dist: click
Requires-Dist: libcst
Requires-Dist: requests
Requires-Dist: requirements-parser>=0.11.0
Provides-Extra: test
Requires-Dist: pandas; extra == "test"
Requires-Dist: parameterized; extra == "test"
Requires-Dist: pytest; extra == "test"
Requires-Dist: pytest-cov; extra == "test"
Dynamic: author
Dynamic: author-email
Dynamic: classifier
Dynamic: description
Dynamic: description-content-type
Dynamic: home-page
Dynamic: keywords
Dynamic: provides-extra
Dynamic: requires-dist
Dynamic: requires-python
Dynamic: summary
